LICENSE.txt
MANIFEST.in
README.rst
setup.py
ebml/__init__.py
ebml/core.py
ebml.egg-info/SOURCES.txt
ebml.egg-info/dependency_links.txt
ebml.egg-info/namespace_packages.txt
ebml.egg-info/requires.txt
ebml.egg-info/top_level.txt
ebml/schema/__init__.py
ebml/schema/base.py
ebml/schema/ebml.py
ebml/schema/matroska.py
ebml/schema/matroska.xml
ebml/schema/specs.py
ebml/tests/__init__.py
ebml/tests/test_core.py
ebml/utils/__init__.py
ebml/utils/dump_structure.py
ebml/utils/ebml_data.py
python_ebml.egg-info/PKG-INFO
python_ebml.egg-info/SOURCES.txt
python_ebml.egg-info/dependency_links.txt
python_ebml.egg-info/not-zip-safe
python_ebml.egg-info/requires.txt
python_ebml.egg-info/top_level.txt
tools/get_first_cluster_timecode.py
tools/get_info.py