Metadata-Version: 1.1
Name: python-ebml
Version: 0.2.1
Summary: EBML (Extensible Binary Meta Language) library for Python
Home-page: https://github.com/yomguy/python-ebml.git
Author: Joseph Spiros
Author-email: joseph@josephspiros.com
License: BSD
Platform: OS Independent
Classifier: Programming Language :: Python
Classifier: Development Status :: 3 - Alpha
Classifier: Operating System :: OS Independent
Classifier: Topic :: Multimedia :: Video
Classifier: Topic :: Software Development :: Libraries :: Python Modules
